rhvoice_wrapper/__init__.py
rhvoice_wrapper/rhvoice_bindings.py
rhvoice_wrapper/rhvoice_proxy.py
rhvoice_wrapper/rhvoice_wrapper.py
rhvoice_wrapper-0.8.0.dist-info/LICENSE.md
rhvoice_wrapper-0.8.0.dist-info/METADATA
rhvoice_wrapper-0.8.0.dist-info/WHEEL
rhvoice_wrapper-0.8.0.dist-info/top_level.txt
rhvoice_wrapper-0.8.0.dist-info/RECORD
