Metadata-Version: 2.1
Name: rhvoice-wrapper
Version: 0.8.0
Summary: High-level interface for RHVoice library
Home-page: https://github.com/Aculeasis/rhvoice-proxy
Author: Aculeasis
Author-email: amilpalimov2@ya.ru
License: GPLv3+
Classifier: Intended Audience :: Developers
Classifier: Programming Language :: Python :: 3
Classifier: License :: OSI Approved :: GNU General Public License v3 or later (GPLv3+)
Classifier: Operating System :: OS Independent
Classifier: Topic :: Multimedia :: Sound/Audio :: Speech
Classifier: Topic :: Software Development :: Libraries
Requires-Python: >=3.5
License-File: LICENSE.md
Provides-Extra: rhvoice
Requires-Dist: rhvoice-wrapper-bin ; extra == 'rhvoice'
